spirodeploy/__main__.py
spirodeploy/builder.py
spirodeploy/cli.py
spirodeploy/client.py
spiro_deploy-0.4.dist-info/LICENSE
spiro_deploy-0.4.dist-info/METADATA
spiro_deploy-0.4.dist-info/WHEEL
spiro_deploy-0.4.dist-info/entry_points.txt
spiro_deploy-0.4.dist-info/top_level.txt
spiro_deploy-0.4.dist-info/RECORD
